dagster_sdf/__init__.py
dagster_sdf/asset_decorator.py
dagster_sdf/asset_utils.py
dagster_sdf/constants.py
dagster_sdf/dagster_sdf_translator.py
dagster_sdf/errors.py
dagster_sdf/py.typed
dagster_sdf/resource.py
dagster_sdf/sdf_cli_event.py
dagster_sdf/sdf_cli_invocation.py
dagster_sdf/sdf_event_iterator.py
dagster_sdf/sdf_information_schema.py
dagster_sdf/sdf_version.py
dagster_sdf/sdf_workspace.py
dagster_sdf/version.py
dagster_sdf/cli/__init__.py
dagster_sdf/cli/app.py
dagster_sdf/include/__init__.py
dagster_sdf/include/pyproject.toml.jinja
dagster_sdf/include/setup.py.jinja
dagster_sdf/include/scaffold/__init__.py.jinja
dagster_sdf/include/scaffold/assets.py.jinja
dagster_sdf/include/scaffold/constants.py.jinja
dagster_sdf/include/scaffold/definitions.py.jinja
dagster_sdf/include/scaffold/schedules.py.jinja
dagster_sdf-0.25.11.dist-info/LICENSE
dagster_sdf-0.25.11.dist-info/METADATA
dagster_sdf-0.25.11.dist-info/WHEEL
dagster_sdf-0.25.11.dist-info/entry_points.txt
dagster_sdf-0.25.11.dist-info/top_level.txt
dagster_sdf-0.25.11.dist-info/RECORD
