Metadata-Version: 2.1
Name: dagster-sdf
Version: 0.25.11
Summary: A Dagster integration for sdf
Home-page: https://github.com/dagster-io/dagster/tree/master/python_modules/libraries/dagster-sdf
Author: SDF Labs
Author-email: hello@sdf.com
License: Apache-2.0
Classifier: Programming Language :: Python :: 3.9
Classifier: Programming Language :: Python :: 3.10
Classifier: Programming Language :: Python :: 3.11
Classifier: Programming Language :: Python :: 3.12
Classifier: License :: OSI Approved :: Apache Software License
Classifier: Operating System :: OS Independent
Requires-Python: >=3.9,<3.13
License-File: LICENSE
Requires-Dist: dagster ==1.9.11
Requires-Dist: sdf-cli <0.3.24,>=0.3.23
Requires-Dist: orjson
Requires-Dist: polars
Requires-Dist: typer >=0.9.0
Provides-Extra: test
